report/__init__.py
report/_config.py
report/_data.py
report/_internal.py
report/attachment_type.py
report/attachments.py
report/core.py
report/item.py
report/plugin.py
report_dh-1.0.dist-info/LICENSE
report_dh-1.0.dist-info/METADATA
report_dh-1.0.dist-info/WHEEL
report_dh-1.0.dist-info/entry_points.txt
report_dh-1.0.dist-info/top_level.txt
report_dh-1.0.dist-info/RECORD
