Metadata-Version: 2.1
Name: report-dh
Version: 1.0
Summary: Report Portal API
Home-page: https://github.com/deyaa562/Report
Author: Deyaa Hojerat
Author-email: deyaa.hojerat.98@gmail.com
License: MIT License
Classifier: Development Status :: 3 - Alpha
Classifier: Intended Audience :: Developers
Classifier: License :: OSI Approved :: MIT License
Classifier: Programming Language :: Python :: 3.7
Classifier: Programming Language :: Python :: 3.8
Classifier: Programming Language :: Python :: 3.9
Classifier: Programming Language :: Python :: 3.10
Classifier: Framework :: Pytest
Requires-Python: >=3.7, <4
License-File: LICENSE
Requires-Dist: requests
Requires-Dist: pytest
